kinimlearn/DTClassifier.py
kinimlearn/DT_Classifier.py
kinimlearn/__init__.py
kinimlearn-0.0.7.dist-info/LICENSE.txt
kinimlearn-0.0.7.dist-info/METADATA
kinimlearn-0.0.7.dist-info/WHEEL
kinimlearn-0.0.7.dist-info/top_level.txt
kinimlearn-0.0.7.dist-info/RECORD
