Metadata-Version: 2.1
Name: kinimlearn
Version: 0.0.7
Summary: Custom Decision Tree
Home-page: http://pypi.python.org/pypi/PackageName/
Author: Mithun Kini
Author-email: kinimithun@gmail.com
License: MIT
Keywords: decision tree
Platform: UNKNOWN
Classifier: Development Status :: 5 - Production/Stable
Classifier: Intended Audience :: Education
Classifier: License :: OSI Approved :: MIT License
Classifier: Operating System :: MacOS :: MacOS X
Classifier: Programming Language :: Python :: 3
License-File: LICENSE.txt
Requires-Dist: numpy
Requires-Dist: pandas
